py_data_provider/__init__.py
py_data_provider/data_providers/__init__.py
py_data_provider/data_providers/base.py
py_data_provider/data_providers/duts.py
py_data_provider/data_providers/nyud.py
py_data_provider/data_providers/voc.py
py_data_provider/datasets/__init__.py
py_data_provider/datasets/base.py
py_data_provider/datasets/duts.py
py_data_provider/datasets/nyud.py
py_data_provider/datasets/voc.py
py_data_provider/parsers/__init__.py
py_data_provider/parsers/yolo.py
py_data_provider/utils/__init__.py
py_data_provider/utils/colors.py
py_data_provider/utils/config.py
py_data_provider/utils/files.py
py_data_provider/utils/images.py
py_data_provider/utils/pylogger.py
py_data_provider-0.1.6.dist-info/LICENSE
py_data_provider-0.1.6.dist-info/METADATA
py_data_provider-0.1.6.dist-info/WHEEL
py_data_provider-0.1.6.dist-info/RECORD
