Metadata-Version: 2.1
Name: py-data-provider
Version: 0.1.6
Summary: 
Home-page: https://github.com/thawro/py-data-provider
Author: thawro
Author-email: tomaszhawro.kontakt@gmail.com
Requires-Python: >=3.11,<3.12
Classifier: Programming Language :: Python :: 3
Classifier: Programming Language :: Python :: 3.11
Requires-Dist: black (>=23.3.0,<24.0.0)
Requires-Dist: colored (>=1.4.4,<2.0.0)
Requires-Dist: colorlog (>=6.7.0,<7.0.0)
Requires-Dist: isort (>=5.12.0,<6.0.0)
Requires-Dist: mat73 (>=0.60,<0.61)
Requires-Dist: matplotlib (>=3.7.2,<4.0.0)
Requires-Dist: numpy (>=1.25.2,<2.0.0)
Requires-Dist: opencv-python (>=4.8.0.76,<5.0.0.0)
Requires-Dist: pillow (>=10.0.0,<11.0.0)
Requires-Dist: pre-commit (>=3.2.2,<4.0.0)
Requires-Dist: pypng (>=0.20220715.0,<0.20220716.0)
Requires-Dist: rich (>=13.3.5,<14.0.0)
Requires-Dist: scipy (==1.10.1)
Requires-Dist: tqdm (>=4.65.0,<5.0.0)
Project-URL: Repository, https://github.com/thawro/py-data-provider
